cvflow/__init__.py
cvflow/io/__init__.py
cvflow/io/input/__init__.py
cvflow/io/input/base.py
cvflow/io/input/image.py
cvflow/io/input/video.py
cvflow/io/output/__init__.py
cvflow/io/output/base.py
cvflow/io/output/display.py
cvflow/io/output/video.py
cvflow/plot/__init__.py
cvflow/plot/bbox.py
cvflow/plot/utils.py
cvflow/runner/__init__.py
cvflow/runner/base.py
cvflow/runner/video.py
cvflow/utils/__init__.py
cvflow/utils/color.py
cvflow/utils/runner.py
cvflow-0.1.1.dist-info/LICENSE
cvflow-0.1.1.dist-info/METADATA
cvflow-0.1.1.dist-info/WHEEL
cvflow-0.1.1.dist-info/RECORD
