Metadata-Version: 2.1
Name: cvflow
Version: 0.1.1
Summary: 
License: Apache-2.0
Author: Minato
Author-email: 82735346+minato-ellie@users.noreply.github.com
Requires-Python: >=3.8.1,<3.11
Classifier: License :: OSI Approved :: Apache Software License
Classifier: Programming Language :: Python :: 3
Classifier: Programming Language :: Python :: 3.9
Classifier: Programming Language :: Python :: 3.10
Requires-Dist: asyncer (>=0.0.2,<0.0.3)
Requires-Dist: numba (>=0.56.4,<0.57.0)
Requires-Dist: opencv-python (>=4.7.0.72,<5.0.0.0)
Requires-Dist: typing-extensions (>=4.5.0,<5.0.0)
